.gitignore
AUTHORS.rst
HISTORY.rst
LICENSE
README.md
_version.py
build_exe.py
environment.yml
installer.nsi
installer.sh
mkdocs.yml
pyproject.toml
setup.py
wrfplot.spec
.github/release.yml
.github/workflows/build-docs.yaml
.github/workflows/release-github.yaml
.github/workflows/release-pip.yaml
docs/authors.md
docs/colormaps.md
docs/contribution.md
docs/index.md
docs/install.md
docs/license.md
docs/support.md
docs/usage.md
docs/variables.md
docs/static/wrfplot.png
docs/static/images/T2_13-05-2021_17_30.png
docs/static/images/T2_13-05-2021_17_30_clevels.png
docs/static/images/T2_cmap-example.png
docs/static/images/rh2-13-05-2021_05_30.gif
docs/static/images/rh2-13-05-2021_05_30_faster.gif
docs/static/images/rh2_13-05-2021_11_31.png
docs/static/images/u_td.png
docs/static/images/u_winds_300_13-05-2021_11_31.png
docs/static/images/screenshots/1-windows-setup.png
docs/static/images/screenshots/2-user-elivation.png
docs/static/images/screenshots/3-windows-welcome-screen.png
docs/static/images/screenshots/4-windows-user-agreement.png
docs/static/images/screenshots/5-windows-install-options.png
docs/static/images/screenshots/6-windows-destination-dir.png
docs/static/images/screenshots/7-windows-install-progress.png
docs/static/images/screenshots/8-windows-install-finish.png
tests/test.py
wrfplot/__init__.py
wrfplot/_version.py
wrfplot/animation.py
wrfplot/arguments.py
wrfplot/convert.py
wrfplot/core.py
wrfplot/fileio.py
wrfplot/plot.py
wrfplot/utils.py
wrfplot/wrfplot.py
wrfplot.egg-info/PKG-INFO
wrfplot.egg-info/SOURCES.txt
wrfplot.egg-info/dependency_links.txt
wrfplot.egg-info/entry_points.txt
wrfplot.egg-info/requires.txt
wrfplot.egg-info/top_level.txt
wrfplot/data/wrf_variables.ini
wrfplot/data/wrfplot.png
wrfplot/data/wxguy.ico
wrfplot/data/shape/world_shape.cpg
wrfplot/data/shape/world_shape.dbf
wrfplot/data/shape/world_shape.prj
wrfplot/data/shape/world_shape.qpj
wrfplot/data/shape/world_shape.shp
wrfplot/data/shape/world_shape.shx
wrfplot/data/shapefiles/natural_earth/physical/ne_10m_coastline.cpg
wrfplot/data/shapefiles/natural_earth/physical/ne_10m_coastline.dbf
wrfplot/data/shapefiles/natural_earth/physical/ne_10m_coastline.prj
