Metadata-Version: 2.4
Name: wrfplot
Version: 3.2.0
Summary: Command line application to plot WRF model output data
Home-page: https://github.com/wxguy/wrfplot
Author: J Sundar
Author-email: J Sundar <wrf.guy@gmail.com>
License-Expression: GPL-3.0-or-later
Project-URL: Bug Reports, https://github.com/wxguy/wrfplot/issues
Project-URL: Source, https://github.com/wxguy/wrfplot/
Project-URL: Homepage, https://github.com/wxguy/wrfplot/
Project-URL: Documentation, https://wrfplot.readthedocs.io
Keywords: WRF,Weather Research and Forecast,Scientific,Engineering,Atmospheric Science,Weather Model,Plotting,Software Development,Numerical Weather Prediction,NWP
Classifier: Programming Language :: Python :: 3.7
Classifier: Programming Language :: Python :: 3.8
Classifier: Programming Language :: Python :: 3.9
Classifier: Programming Language :: Python :: 3.10
Classifier: Programming Language :: Python :: 3.11
Classifier: Operating System :: Unix
Classifier: Operating System :: Microsoft :: Windows
Classifier: Programming Language :: Python :: Implementation :: CPython
Requires-Python: >=3.7.0
License-File: LICENSE
License-File: AUTHORS.rst
Requires-Dist: cartopy
Requires-Dist: xarray
Requires-Dist: matplotlib
Requires-Dist: wrf-python>=1.3
Requires-Dist: tqdm
Requires-Dist: netcdf4
Requires-Dist: colormaps
Dynamic: author
Dynamic: home-page
Dynamic: license-file
Dynamic: requires-python
